setup.py
simpleweixin/__init__.py
simpleweixin/weixinsdk.py
simpleweixin.egg-info/PKG-INFO
simpleweixin.egg-info/SOURCES.txt
simpleweixin.egg-info/dependency_links.txt
simpleweixin.egg-info/top_level.txt