Metadata-Version: 1.0
Name: simpleweixin
Version: 0.0.0.1.pre
Summary: a simple weixin public platform sdk of python
Home-page: https://github.com/ipconfiger/simpleweixin
Author: Alexander.Li
Author-email: superpowerlee@gmail.com
License: LGPL
Keywords: github pages blog
Platform: UNKNOWN
